reddacted/__init__.py
reddacted/cli.py
reddacted/cli_config.py
reddacted/llm_detector.py
reddacted/pii_detector.py
reddacted/results.py
reddacted/sentiment.py
reddacted/styles.py
reddacted/textual_cli.py
reddacted/textual_ui.py
reddacted/version.py
reddacted/api/__init__.py
reddacted/api/api.py
reddacted/api/list_models.py
reddacted/api/reddit.py
reddacted/api/scraper.py
reddacted/ui/__init__.py
reddacted/ui/comment_actions.py
reddacted/ui/details_screen.py
reddacted/utils/__init__.py
reddacted/utils/analysis.py
reddacted/utils/base.py
reddacted/utils/log_handler.py
reddacted/utils/panels.py
reddacted/utils/progress.py
reddacted/utils/report.py
reddacted/utils/tables.py
reddacted-0.2.6.dist-info/licenses/LICENSE
reddacted-0.2.6.dist-info/METADATA
reddacted-0.2.6.dist-info/WHEEL
reddacted-0.2.6.dist-info/entry_points.txt
reddacted-0.2.6.dist-info/top_level.txt
reddacted-0.2.6.dist-info/RECORD
