Metadata-Version: 2.4
Name: reddacted
Version: 0.2.6
Summary: Analyze Reddit comments for PII and other sensitive information using local or OpenAI API compatible LLMs and perform sentiment analysis, edit and remove comments.
Author-email: Taylor Wilsdon <taylor@taylorwilsdon.com>
License: MIT License
Project-URL: Bug Tracker, https://github.com/taylorwilsdon/reddacted/issues
Keywords: reddact,reddacted,reddit,llm,pii,sentiment,analysis,nlp
Classifier: Development Status :: 3 - Alpha
Classifier: Intended Audience :: Science/Research
Classifier: License :: OSI Approved :: MIT License
Classifier: Programming Language :: Python :: 3
Classifier: Programming Language :: Python :: 3.11
Classifier: Environment :: Console
Classifier: Topic :: Text Processing :: Linguistic
Classifier: Topic :: Scientific/Engineering :: Artificial Intelligence
Requires-Python: >=3.11
License-File: LICENSE
Requires-Dist: autopage>=0.5.2
Requires-Dist: praw>=7.7.1
Requires-Dist: nltk>=3.8.1
Requires-Dist: requests>=2.31.0
Requires-Dist: six>=1.16.0
Requires-Dist: httpx==0.27.2
Requires-Dist: openai>=1.3.7
Requires-Dist: rich>=13.7.0
Requires-Dist: textual==2.1.2
Requires-Dist: urllib3==2.3.0
Provides-Extra: dev
Requires-Dist: pytest; extra == "dev"
Requires-Dist: black; extra == "dev"
Requires-Dist: mypy; extra == "dev"
Requires-Dist: ruff; extra == "dev"
Requires-Dist: uv; extra == "dev"
Requires-Dist: tomli>=2.0.0; extra == "dev"
Dynamic: license-file
